metoryx/__init__.py
metoryx/initializers.py
metoryx/utils.py
metoryx/_src/__init__.py
metoryx/_src/activations.py
metoryx/_src/activations_test.py
metoryx/_src/base.py
metoryx/_src/base_test.py
metoryx/_src/dropout.py
metoryx/_src/dropout_test.py
metoryx/_src/initializers.py
metoryx/_src/initializers_test.py
metoryx/_src/linear.py
metoryx/_src/linear_test.py
metoryx/_src/meter.py
metoryx/_src/normalization.py
metoryx/_src/normalization_test.py
metoryx/_src/padding.py
metoryx/_src/padding_test.py
metoryx/_src/pool.py
metoryx/_src/pool_test.py
metoryx/_src/utils.py
metoryx-0.0.1a0.dist-info/licenses/LICENSE
metoryx-0.0.1a0.dist-info/METADATA
metoryx-0.0.1a0.dist-info/WHEEL
metoryx-0.0.1a0.dist-info/top_level.txt
metoryx-0.0.1a0.dist-info/RECORD
