Metadata-Version: 2.4
Name: metoryx
Version: 0.0.1a0
Summary: A neural network library for JAX that combines functional init/apply style with a flexible model definition.
Classifier: Development Status :: 3 - Alpha
Requires-Python: >=3.12
License-File: LICENSE
Requires-Dist: jax>=0.7.1
Requires-Dist: jaxlib>=0.7.1
Dynamic: license-file
